lowdash/__init__.py
lowdash/_utils.py
lowdash/arrays.py
lowdash/strings.py
lowdash-1.6.0.dist-info/WHEEL
lowdash-1.6.0.dist-info/METADATA
lowdash-1.6.0.dist-info/RECORD
